{"Angell": "id_0", "Bernanke": "id_1", "Bies": "id_2", "Black": "id_3", "Blinder": "id_4", "Boehne": "id_5", "Boykin": "id_6", "Broaddus": "id_7", "Corrigan": "id_8", "Cumming": "id_9", "Duke": "id_10", "Evans": "id_11", "Ferguson": "id_12", "Fisher": "id_13", "Forrestal": "id_14", "Geithner": "id_15", "Gramlich": "id_16", "Greenspan": "id_17", "Guffey": "id_18", "Guynn": "id_19", "Heller": "id_20", "Hoenig": "id_21", "Hoskins": "id_22", "Johnson": "id_23", "Jordan": "id_24", "Keehn": "id_25", "Kelley": "id_26", "Kohn": "id_27", "Kroszner": "id_28", "LaWare": "id_29", "Lacker": "id_30", "Lindsey": "id_31", "McDonough": "id_32", "McTeer": "id_33", "Melzer": "id_34", "Meyer": "id_35", "Minehan": "id_36", "Mishkin": "id_37", "Moskow": "id_38", "Mullins": "id_39", "Olson": "id_40", "Parry": "id_41", "Phillips": "id_42", "Pianalto": "id_43", "Plosser": "id_44", "Poole": "id_45", "Prell": "id_46", "Rivlin": "id_47", "Rosengren": "id_48", "Santomero": "id_49", "Seger": "id_50", "Stern": "id_51", "Syron": "id_52", "Truman": "id_53", "Warsh": "id_54", "White": "id_55", "Yellen": "id_56"}